MANIFEST.in
README.rst
setup.py
collective/__init__.py
collective.microdata.contentlisting.egg-info/PKG-INFO
collective.microdata.contentlisting.egg-info/SOURCES.txt
collective.microdata.contentlisting.egg-info/dependency_links.txt
collective.microdata.contentlisting.egg-info/entry_points.txt
collective.microdata.contentlisting.egg-info/namespace_packages.txt
collective.microdata.contentlisting.egg-info/not-zip-safe
collective.microdata.contentlisting.egg-info/requires.txt
collective.microdata.contentlisting.egg-info/top_level.txt
collective/microdata/__init__.py
collective/microdata/contentlisting/__init__.py
collective/microdata/contentlisting/configure.zcml
collective/microdata/contentlisting/interfaces.py
collective/microdata/contentlisting/testing.py
collective/microdata/contentlisting/browser/__init__.py
collective/microdata/contentlisting/browser/configure.zcml
collective/microdata/contentlisting/browser/view.py
collective/microdata/contentlisting/browser/templates/folder_listing.pt
collective/microdata/contentlisting/browser/templates/folder_listing_item.pt
collective/microdata/contentlisting/browser/templates/folder_summary_view.pt
collective/microdata/contentlisting/browser/templates/folder_summary_view_item.pt
collective/microdata/contentlisting/profiles/default/browserlayer.xml
collective/microdata/contentlisting/profiles/default/metadata.xml
collective/microdata/contentlisting/tests/__init__.py
collective/microdata/contentlisting/tests/base.py
collective/microdata/contentlisting/tests/test_microdata_contents.py
docs/HISTORY.txt
docs/INSTALL.txt
docs/LICENSE.GPL
docs/LICENSE.txt