Metadata-Version: 1.1
Name: collective.microdata.contentlisting
Version: 0.1
Summary: Folders and collections listing support for microdata in Plone
Home-page: https://github.com/keul/collective.microdata.contentlisting
Author: keul
Author-email: luca@keul.it
License: GPL
Keywords: plone microdata schema.org html5 listing folder
Platform: UNKNOWN
Classifier: Development Status :: 3 - Alpha
Classifier: Framework :: Plone
Classifier: Framework :: Plone :: 4.2
Classifier: Programming Language :: Python
